Jabberjay/jabberjay.py
Jabberjay/Models/Classical/feature_extraction.py
Jabberjay/Models/Classical/run.py
Jabberjay/Models/RawNet2/model.py
Jabberjay/Models/RawNet2/model_config_RawNet.yaml
Jabberjay/Models/RawNet2/run.py
Jabberjay/Models/Tranformer/AST/run.py
Jabberjay/Models/Tranformer/VIT/utility.py
Jabberjay/Models/Tranformer/VIT/ConstantQ/run.py
Jabberjay/Models/Tranformer/VIT/MFCC/run.py
Jabberjay/Models/Tranformer/VIT/MelSpectrogram/run.py
Jabberjay/Utilities/enum_handler.py
Jabberjay/Utilities/hugging_face.py
jabberjay-0.0.4.dist-info/METADATA
jabberjay-0.0.4.dist-info/WHEEL
jabberjay-0.0.4.dist-info/entry_points.txt
jabberjay-0.0.4.dist-info/licenses/LICENSE
jabberjay-0.0.4.dist-info/RECORD
