Metadata-Version: 2.3
Name: Jabberjay
Version: 0.0.4
Summary: 🦜 Synthetic Voice Detection
Project-URL: Homepage, https://github.com/MattyB95/Jabberjay
Project-URL: Bug Tracker, https://github.com/MattyB95/Jabberjay/issues
Author-email: Matthew Boakes <mboakes@turing.ac.uk>
License-Expression: MIT
License-File: LICENSE
Keywords: Detection,Synthetic,Voice
Classifier: License :: OSI Approved :: MIT License
Classifier: Operating System :: OS Independent
Classifier: Programming Language :: Python :: 3
Requires-Python: <3.12,>=3.10
Requires-Dist: joblib
Requires-Dist: librosa
Requires-Dist: matplotlib
Requires-Dist: numpy
Requires-Dist: pillow
Requires-Dist: pyyaml
Requires-Dist: scikit-learn
Requires-Dist: soundfile
Requires-Dist: torch
Requires-Dist: transformers
Provides-Extra: dev
Requires-Dist: build; extra == 'dev'
Requires-Dist: pre-commit; extra == 'dev'
Requires-Dist: twine; extra == 'dev'
